nmigate/__init__.py
nmigate/lib/__init__.py
nmigate/lib/billing.py
nmigate/lib/customer_vault.py
nmigate/lib/nmi.py
nmigate/lib/plans.py
nmigate/lib/subscriptions.py
nmigate/lib/transactions.py
nmigate/util/__init__.py
nmigate/util/wrappers.py
nmigate-0.0.23.dist-info/LICENSE
nmigate-0.0.23.dist-info/METADATA
nmigate-0.0.23.dist-info/WHEEL
nmigate-0.0.23.dist-info/top_level.txt
nmigate-0.0.23.dist-info/RECORD
