Metadata-Version: 2.1
Name: nmigate
Version: 0.0.23
Summary: A Nmi library for python
Author-email: Gustavo <gustavo.gordillo.giron@gmail.com>
Classifier: Programming Language :: Python :: 3
Classifier: License :: OSI Approved :: MIT License
Classifier: Operating System :: OS Independent
Requires-Python: >=3.8
License-File: LICENSE
